pipertool/__init__.py
pipertool/example.py
pipertool/py.typed
pipertool-0.0.2.dist-info/LICENSE
pipertool-0.0.2.dist-info/WHEEL
pipertool-0.0.2.dist-info/METADATA
pipertool-0.0.2.dist-info/RECORD
