Metadata-Version: 2.1
Name: pipertool
Version: 0.0.2
Summary: Piper is an open-source platform for data science and machine learning prototyping.
Home-page: https://github.com/TatraDev/pipertool/tree/pipertool_pypi
License: Apache-2.0
Requires-Python: >=3.7,<4.0
Classifier: Development Status :: 1 - Planning
Classifier: Intended Audience :: Developers
Classifier: License :: OSI Approved :: Apache Software License
Classifier: Operating System :: OS Independent
Classifier: Programming Language :: Python :: 3
Classifier: Programming Language :: Python :: 3.10
Classifier: Programming Language :: Python :: 3.7
Classifier: Programming Language :: Python :: 3.8
Classifier: Programming Language :: Python :: 3.9
Classifier: Topic :: Software Development :: Libraries :: Python Modules
Provides-Extra: docs
Requires-Dist: m2r2 (>=0.3,<0.4); extra == "docs"
Requires-Dist: sphinx (>=5.1,<6.0); extra == "docs"
Requires-Dist: sphinx-autodoc-typehints (>=1.19,<2.0); extra == "docs"
Requires-Dist: tomlkit (>=0.11,<0.12); extra == "docs"
Project-URL: Repository, https://github.com/TatraDev/pipertool/tree/pipertool_pypi
